Metadata-Version: 2.1
Name: locust-graphql-client
Version: 0.2.0
Summary: Locust GraphQL client GraphQL. This is a GraphQLLocust equivalent of HttpLocust
Home-page: https://github.com/rohitghatol/locust-graphql-client
Author: rohitghatol
Author-email: 
License: Apache License 2.0
Platform: UNKNOWN
